{
  "slug": "pixabay-watermark-free-images",
  "category": "watermark-removal",
  "tool": "remove-watermark",
  "lang": "tr",
  "title": "Pixabay'da Filigransız Görseller İçin Kılavuz",
  "description": "Pixabay Su İşareti Olmayan Görseller Rehberi. FixPic'in ücretsiz çevrimiçi aracıyla AI su işareti kaldırma. Üyelik gerektirmez.",
  "keywords": [
    "su işareti kaldırma",
    "su işareti silici",
    "su işaretini sil",
    "su işaretini silme",
    "pixabay",
    "su işareti olmadan",
    "görseller"
  ],
  "content": "## Giriş\n\nPixabay Su İşareti Olmayan Görseller Rehberi, birçok kişinin çevrimiçi olarak aradığı bir konudur. Kendi görsellerinizle çalışıyor ya da yasal alternatifleri araştırıyorsanız, seçeneklerinizi anlamak önemlidir.\n\nBu rehber, pixabay su işareti olmayan görseller rehberi hakkında bilmeniz gereken her şeyi kapsar; yasal hususlar ve en iyi uygulamalar dahil.\n\n## Su İşaretlerini Anlamak\n\nSu işaretleri birkaç amaca hizmet eder:\n\n- **Telif hakkı koruması**: Fotoğrafçılar ve sanatçılar, eserlerini korumak için su işareti kullanır\n- **Markalaşma**: Şirketler, marka varlığını sürdürmek için su işareti ekler\n- **Önizleme koruması**: Stok fotoğraf siteleri, önizleme görsellerinde su işareti kullanır\n\nHerhangi bir su işaretini kaldırmadan önce, bunu yapma hakkınızın olup olmadığını düşünün.\n\n## Yasal Hususlar\n\nSu işareti kaldırma, önemli yasal soruları gündeme getirir:\n\n### Kaldırmanın Kabul Edilebilir Olduğu Durumlar\n- Kendi görsellerinizden su işaretlerini kaldırmak\n- Lisansladığınız görsellerle çalışmak\n- Kişisel fotoğraflardaki tarih damgalarını veya kamera su işaretlerini kaldırmak\n- Bazı yargı bölgelerinde eğitim veya kişisel kullanım\n\n### Kaldırmanın KABUL EDİLEMEYECEĞİ Durumlar\n- Stok fotoğraflar için ödeme yapmaktan kaçınmak amacıyla su işaretlerini kaldırmak\n- Lisans olmadan su işareti olan görsellerin ticari kullanımı\n- Başkalarının eserlerinden telif hakkı bildirimlerini kaldırmak\n\n## FixPic'in Su İşareti Kaldırma Süreci\n\n### Adım 1: Görselinizi Yükleyin\n\nKaldırmak istediğiniz su işareti olan bir görsel seçin. Araçlarımız en iyi şekilde çalışır:\n- Yarı saydam su işaretleri\n- Metin üst katmanları\n- Logo su işaretleri\n- Tarih damgaları ve zaman damgaları\n\n### Adım 2: AI İşleme\n\nYapay zeka, görseli analiz eder ve su işaretinin arkasındaki alanı akıllıca yeniden yapılandırmak için gelişmiş inpainting teknolojisini kullanır.\n\n### Adım 3: Temiz Görseli İndirin\n\nSu işareti olmayan görselinizi saniyeler içinde alın. Yapay zeka, doğal görünümlü sonuçlar için dokuları, renkleri ve detayları korur.\n\n## Alternatif Seçenekler\n\nSu işareti olmayan görsellere ihtiyacınız varsa, bu yasal alternatifleri değerlendirin:\n\n### Ücretsiz Stok Fotoğraf Siteleri\n- **Unsplash** - Yüksek kaliteli ücretsiz fotoğraflar\n- **Pexels** - Ücretsiz stok fotoğraflar ve videolar\n- **Pixabay** - Geniş bir ücretsiz görsel kütüphanesi\n- **Burst by Shopify** - Ücretsiz ticari kullanım fotoğrafları\n\n### Uygun Fiyatlı Stok Abonelikleri\n- Birçok stok sitesi uygun fiyatlı aylık planlar sunar\n- Eğitim indirimleri genellikle mevcuttur\n- Bireysel görsel satın almayı düşünün\n\n## En İyi Uygulamalar\n\n1. **Her zaman hakları doğrulayın** - Görseli değiştirmek için izniniz olduğundan emin olun\n2. **Orijinal dosyaları saklayın** - Gerekirse orijinalini kaydedin\n3. **Yüksek kaliteli kaynaklar kullanın** - Daha iyi giriş, daha iyi sonuçlar üretir\n4. **Sonuçları dikkatlice kontrol edin** - Kaliteyi doğrulamak için yakınlaştırın\n\n## Sıkça Sorulan Sorular\n\n### AI her su işaretini kaldırabilir mi?\nYapay zeka, en iyi yarı saydam ve metin su işaretleriyle çalışır. Çok büyük veya karmaşık su işaretleri tamamen kaldırılmayabilir.\n\n### Su işaretini kaldırmak görsel kalitesini düşürür mü?\nYapay zekamız, su işaretlerini kaldırırken görsel kalitesini korumak için tasarlanmıştır. Sonuçlar, su işaretinin karmaşıklığına ve konumuna bağlıdır.\n\n### Bu hizmet ücretsiz mi?\nEvet, FixPic'in su işareti kaldırma aracı tamamen ücretsizdir ve kayıt gerektirmez.\n\n## Sonuç\n\nPixabay Su İşareti Olmayan Görseller Rehberi, hem teknik süreci hem de yasal sonuçları anlamayı gerektirir. FixPic, yasal su işareti kaldırma ihtiyaçları için güçlü ve ücretsiz bir araç sunar.\n\nHerhangi bir su işareti kaldırma aracını kullanmadan önce, görselleri değiştirme hakkına sahip olduğunuzdan emin olun. Şüphe durumunda, mevcut olan birçok ücretsiz ve uygun fiyatlı stok fotoğraf alternatifini keşfedin.",
  "publishedAt": "2026-01-04T02:49:15.129Z",
  "updatedAt": "2026-01-12T11:43:29.917Z",
  "readingTime": 3,
  "relatedArticles": [
    "remove-transparent-watermark",
    "remove-istock-watermark",
    "royalty-free-image-sources"
  ]
}
